pylake/__init__.py
pylake/functions.py
pylake/functions_meta.py
pylake/pylake.py
pylake/pylake_metabolizer.py
pylake-0.1.12.dist-info/METADATA
pylake-0.1.12.dist-info/WHEEL
pylake-0.1.12.dist-info/top_level.txt
pylake-0.1.12.dist-info/RECORD
