Metadata-Version: 2.1
Name: pylake
Version: 0.1.12
Summary: pylake
Home-page: https://github.com/eawag-surface-waters-research/pylake
Author: Hugo Cruz
Author-email: <huggcruzz@gmail.com>
License: MIT
Keywords: python,pylake,Lake analyzer,environmental data,Physical properties
Requires-Dist: numpy>=1.19.5
Requires-Dist: pandas>=1.1.5
Requires-Dist: PyYAML>=6.0
Requires-Dist: scipy>=1.5.4
Requires-Dist: dask>=2022.02.1
Requires-Dist: xarray>=0.19.0
Requires-Dist: seawater>=3.3.4
